{
  "properties": {
    "Created": {
      "type": [
        "date-time"
      ]
    },
    "Creator": {
      "type": [
        "integer"
      ]
    },
    "Credit": {
      "type": [
        "number"
      ]
    },
    "Date": {
      "type": [
        "date"
      ]
    },
    "Description": {
      "type": [
        "string"
      ]
    },
    "Id": {
      "type": [
        "integer"
      ]
    },
    "Modified": {
      "type": [
        "date-time"
      ]
    },
    "Type": {
      "type": [
        "integer"
      ]
    }
  }
}