{
  "properties": {
    "campaignId": {
      "type": [
        "null",
        "integer"
      ]
    },
    "catalogCollectionCount": {
      "type": [
        "null",
        "integer"
      ]
    },
    "catalogLookupCount": {
      "type": [
        "null",
        "integer"
      ]
    },
    "channelId": {
      "type": [
        "null",
        "integer"
      ]
    },
    "contentId": {
      "type": [
        "null",
        "integer"
      ]
    },
    "createdAt": {
      "type": [
        "null",
        "date-time"
      ]
    },
    "email": {
      "type": [
        "null",
        "string"
      ]
    },
    "espName": {
      "type": [
        "null",
        "string"
      ]
    },
    "itblInternal": {
      "properties": {
        "documentCreatedAt": {
          "type": [
            "null",
            "date-time"
          ]
        },
        "documentUpdatedAt": {
          "type": [
            "null",
            "date-time"
          ]
        }
      },
      "type": [
        "null",
        "object"
      ]
    },
    "messageBusId": {
      "type": [
        "null",
        "string"
      ]
    },
    "messageId": {
      "type": [
        "null",
        "string"
      ]
    },
    "messageTypeId": {
      "type": [
        "null",
        "integer"
      ]
    },
    "productRecommendationCount": {
      "type": [
        "null",
        "integer"
      ]
    },
    "templateId": {
      "type": [
        "null",
        "integer"
      ]
    },
    "transactionalData": {
      "properties": {
        "campaignId": {
          "type": [
            "null",
            "integer"
          ]
        },
        "categories": {
          "items": {},
          "type": [
            "null",
            "array"
          ]
        },
        "compare_at_price": {
          "type": [
            "null",
            "number"
          ]
        },
        "createdAt": {
          "type": [
            "null",
            "date-time"
          ]
        },
        "description": {
          "type": [
            "null",
            "string"
          ]
        },
        "discount": {
          "type": [
            "null",
            "integer"
          ]
        },
        "email": {
          "type": [
            "null",
            "string"
          ]
        },
        "eventName": {
          "type": [
            "null",
            "string"
          ]
        },
        "eventUpdatedAt": {
          "type": [
            "null",
            "date-time"
          ]
        },
        "handle": {
          "type": [
            "null",
            "string"
          ]
        },
        "id": {
          "type": [
            "null",
            "string"
          ]
        },
        "imageUrl": {
          "type": [
            "null",
            "string"
          ]
        },
        "inventory": {
          "type": [
            "null",
            "integer"
          ]
        },
        "itblInternal": {
          "properties": {
            "documentCreatedAt": {
              "type": [
                "null",
                "date-time"
              ]
            },
            "documentUpdatedAt": {
              "type": [
                "null",
                "date-time"
              ]
            }
          },
          "type": [
            "null",
            "object"
          ]
        },
        "name": {
          "type": [
            "null",
            "string"
          ]
        },
        "price": {
          "type": [
            "null",
            "integer"
          ]
        },
        "product_id": {
          "type": [
            "null",
            "string"
          ]
        },
        "product_type": {
          "type": [
            "null",
            "string"
          ]
        },
        "sku": {
          "type": [
            "null",
            "string"
          ]
        },
        "templateId": {
          "type": [
            "null",
            "integer"
          ]
        },
        "url": {
          "type": [
            "null",
            "string"
          ]
        },
        "vendor": {
          "type": [
            "null",
            "string"
          ]
        }
      },
      "type": [
        "null",
        "object"
      ]
    }
  },
  "type": [
    "null",
    "object"
  ]
}