{
  "properties": {
    "_class": {
      "type": [
        "varies"
      ]
    },
    "account": {
      "type": [
        "varies"
      ]
    },
    "address": {
      "type": [
        "string"
      ]
    },
    "balance": {
      "type": [
        "number",
        " string"
      ]
    },
    "batchNumber": {
      "type": [
        "string"
      ]
    },
    "createdDate": {
      "type": [
        "date-time"
      ]
    },
    "department": {
      "type": [
        "varies"
      ]
    },
    "entity": {
      "type": [
        "varies"
      ]
    },
    "externalId": {
      "type": [
        "string"
      ]
    },
    "internalId": {
      "type": [
        "string"
      ]
    },
    "lastModifiedDate": {
      "type": [
        "date-time"
      ]
    },
    "location": {
      "type": [
        "varies"
      ]
    },
    "memo": {
      "type": [
        "string"
      ]
    },
    "nullFieldList": {
      "type": [
        "varies"
      ]
    },
    "payContribList": {
      "type": [
        "varies"
      ]
    },
    "payDeductList": {
      "type": [
        "varies"
      ]
    },
    "payDisburseList": {
      "type": [
        "varies"
      ]
    },
    "payEarnList": {
      "type": [
        "varies"
      ]
    },
    "payExpList": {
      "type": [
        "varies"
      ]
    },
    "payFrequency": {
      "type": [
        "string"
      ]
    },
    "payPtoList": {
      "type": [
        "varies"
      ]
    },
    "paySummaryList": {
      "type": [
        "varies"
      ]
    },
    "payTaxList": {
      "type": [
        "varies"
      ]
    },
    "payTimeList": {
      "type": [
        "varies"
      ]
    },
    "periodEnding": {
      "type": [
        "date-time"
      ]
    },
    "postingPeriod": {
      "type": [
        "varies"
      ]
    },
    "status": {
      "type": [
        "string"
      ]
    },
    "tranDate": {
      "type": [
        "date-time"
      ]
    },
    "tranId": {
      "type": [
        "string"
      ]
    },
    "userAmount": {
      "type": [
        "number",
        " string"
      ]
    },
    "workplace": {
      "type": [
        "varies"
      ]
    }
  }
}