{
  "properties": {
    "_class": {
      "type": [
        "varies"
      ]
    },
    "approvalStatus": {
      "type": [
        "varies"
      ]
    },
    "billingClass": {
      "type": [
        "string"
      ]
    },
    "caseTaskEvent": {
      "type": [
        "varies"
      ]
    },
    "createdDate": {
      "type": [
        "date-time"
      ]
    },
    "customFieldList": {
      "type": [
        "varies"
      ]
    },
    "customer": {
      "type": [
        "varies"
      ]
    },
    "department": {
      "type": [
        "varies"
      ]
    },
    "externalId": {
      "type": [
        "string"
      ]
    },
    "hours": {
      "type": [
        "varies"
      ]
    },
    "internalId": {
      "type": [
        "string"
      ]
    },
    "isBillable": {
      "type": [
        "boolean",
        " string"
      ]
    },
    "item": {
      "type": [
        "varies"
      ]
    },
    "lastModifiedDate": {
      "type": [
        "date-time"
      ]
    },
    "location": {
      "type": [
        "varies"
      ]
    },
    "memo": {
      "type": [
        "string"
      ]
    },
    "nullFieldList": {
      "type": [
        "varies"
      ]
    },
    "overrideRate": {
      "type": [
        "boolean",
        " string"
      ]
    },
    "paidExternally": {
      "type": [
        "boolean",
        " string"
      ]
    },
    "payrollItem": {
      "type": [
        "varies"
      ]
    },
    "price": {
      "type": [
        "varies"
      ]
    },
    "rate": {
      "type": [
        "number",
        " string"
      ]
    },
    "subsidiary": {
      "type": [
        "varies"
      ]
    },
    "timeType": {
      "type": [
        "varies"
      ]
    }
  }
}