{
  "properties": {
    "_class": {
      "type": [
        "varies"
      ]
    },
    "_type": {
      "type": [
        "string"
      ]
    },
    "accessibilityTypeFedEx": {
      "type": [
        "varies"
      ]
    },
    "account": {
      "type": [
        "varies"
      ]
    },
    "accountingApproval": {
      "type": [
        "boolean",
        " string"
      ]
    },
    "accountingBook": {
      "type": [
        "varies"
      ]
    },
    "accountingBookDetailList": {
      "type": [
        "varies"
      ]
    },
    "actualShipDate": {
      "type": [
        "date-time"
      ]
    },
    "address": {
      "type": [
        "string"
      ]
    },
    "adjLocation": {
      "type": [
        "varies"
      ]
    },
    "advance": {
      "type": [
        "number",
        " string"
      ]
    },
    "altHandlingCost": {
      "type": [
        "number",
        " string"
      ]
    },
    "altSalesTotal": {
      "type": [
        "number",
        " string"
      ]
    },
    "altShippingCost": {
      "type": [
        "number",
        " string"
      ]
    },
    "amount": {
      "type": [
        "number",
        " string"
      ]
    },
    "amountPaid": {
      "type": [
        "number",
        " string"
      ]
    },
    "amountRemaining": {
      "type": [
        "number",
        " string"
      ]
    },
    "ancillaryEndorsementFedEx": {
      "type": [
        "varies"
      ]
    },
    "apAcct": {
      "type": [
        "varies"
      ]
    },
    "applied": {
      "type": [
        "number",
        " string"
      ]
    },
    "applyList": {
      "type": [
        "varies"
      ]
    },
    "approvalStatus": {
      "type": [
        "varies"
      ]
    },
    "approved": {
      "type": [
        "boolean",
        " string"
      ]
    },
    "arAcct": {
      "type": [
        "varies"
      ]
    },
    "assemblyItem": {
      "type": [
        "varies"
      ]
    },
    "authCode": {
      "type": [
        "string"
      ]
    },
    "autoApply": {
      "type": [
        "boolean",
        " string"
      ]
    },
    "autoCalculateLag": {
      "type": [
        "boolean",
        " string"
      ]
    },
    "availableVendorCredit": {
      "type": [
        "number",
        " string"
      ]
    },
    "b13AFilingOptionFedEx": {
      "type": [
        "varies"
      ]
    },
    "b13AStatementDataFedEx": {
      "type": [
        "string"
      ]
    },
    "backupEmailAddressFedEx": {
      "type": [
        "string"
      ]
    },
    "backupEmailAddressUps": {
      "type": [
        "string"
      ]
    },
    "balance": {
      "type": [
        "number",
        " string"
      ]
    },
    "billAddressList": {
      "type": [
        "varies"
      ]
    },
    "billOfMaterials": {
      "type": [
        "varies"
      ]
    },
    "billOfMaterialsRevision": {
      "type": [
        "varies"
      ]
    },
    "billPay": {
      "type": [
        "boolean",
        " string"
      ]
    },
    "billingAccount": {
      "type": [
        "varies"
      ]
    },
    "billingAddress": {
      "type": [
        "varies"
      ]
    },
    "billingSchedule": {
      "type": [
        "varies"
      ]
    },
    "binNumbers": {
      "type": [
        "string"
      ]
    },
    "blanketEndDateUps": {
      "type": [
        "date-time"
      ]
    },
    "blanketStartDateUps": {
      "type": [
        "date-time"
      ]
    },
    "bookingConfirmationNumFedEx": {
      "type": [
        "string"
      ]
    },
    "buildable": {
      "type": [
        "number",
        " string"
      ]
    },
    "built": {
      "type": [
        "number",
        " string"
      ]
    },
    "canHaveStackable": {
      "type": [
        "boolean",
        " string"
      ]
    },
    "carrierIdUps": {
      "type": [
        "string"
      ]
    },
    "cashBackList": {
      "type": [
        "varies"
      ]
    },
    "ccApproved": {
      "type": [
        "boolean",
        " string"
      ]
    },
    "ccAvsStreetMatch": {
      "type": [
        "varies"
      ]
    },
    "ccAvsZipMatch": {
      "type": [
        "varies"
      ]
    },
    "ccExpireDate": {
      "type": [
        "date-time"
      ]
    },
    "ccIsPurchaseCardBin": {
      "type": [
        "boolean",
        " string"
      ]
    },
    "ccName": {
      "type": [
        "string"
      ]
    },
    "ccNumber": {
      "type": [
        "string"
      ]
    },
    "ccProcessAsPurchaseCard": {
      "type": [
        "boolean",
        " string"
      ]
    },
    "ccSecurityCode": {
      "type": [
        "string"
      ]
    },
    "ccSecurityCodeMatch": {
      "type": [
        "varies"
      ]
    },
    "ccStreet": {
      "type": [
        "string"
      ]
    },
    "ccZipCode": {
      "type": [
        "string"
      ]
    },
    "chargeIt": {
      "type": [
        "boolean",
        " string"
      ]
    },
    "checkNum": {
      "type": [
        "string"
      ]
    },
    "companyContributionList": {
      "type": [
        "varies"
      ]
    },
    "companyTaxList": {
      "type": [
        "varies"
      ]
    },
    "complete": {
      "type": [
        "boolean",
        " string"
      ]
    },
    "completedQuantity": {
      "type": [
        "number",
        " string"
      ]
    },
    "componentList": {
      "type": [
        "varies"
      ]
    },
    "contribPct": {
      "type": [
        "string"
      ]
    },
    "costComponentList": {
      "type": [
        "varies"
      ]
    },
    "createdDate": {
      "type": [
        "date-time"
      ]
    },
    "createdFrom": {
      "type": [
        "varies"
      ]
    },
    "createdFromShipGroup": {
      "type": [
        "integer",
        " string"
      ]
    },
    "creditCard": {
      "type": [
        "varies"
      ]
    },
    "creditCardProcessor": {
      "type": [
        "varies"
      ]
    },
    "creditLimit": {
      "type": [
        "number",
        " string"
      ]
    },
    "creditList": {
      "type": [
        "varies"
      ]
    },
    "currency": {
      "type": [
        "varies"
      ]
    },
    "currencyName": {
      "type": [
        "string"
      ]
    },
    "customFieldList": {
      "type": [
        "varies"
      ]
    },
    "customForm": {
      "type": [
        "varies"
      ]
    },
    "customer": {
      "type": [
        "varies"
      ]
    },
    "debitCardIssueNo": {
      "type": [
        "string"
      ]
    },
    "deductionList": {
      "type": [
        "varies"
      ]
    },
    "deferredRevenue": {
      "type": [
        "number",
        " string"
      ]
    },
    "depDate": {
      "type": [
        "date-time"
      ]
    },
    "department": {
      "type": [
        "varies"
      ]
    },
    "deposit": {
      "type": [
        "varies"
      ]
    },
    "depositList": {
      "type": [
        "varies"
      ]
    },
    "discountAmount": {
      "type": [
        "number",
        " string"
      ]
    },
    "discountDate": {
      "type": [
        "date-time"
      ]
    },
    "discountItem": {
      "type": [
        "varies"
      ]
    },
    "discountRate": {
      "type": [
        "string"
      ]
    },
    "discountTotal": {
      "type": [
        "number",
        " string"
      ]
    },
    "drAccount": {
      "type": [
        "varies"
      ]
    },
    "dueDate": {
      "type": [
        "date-time"
      ]
    },
    "earningList": {
      "type": [
        "varies"
      ]
    },
    "eccNumberUps": {
      "type": [
        "string"
      ]
    },
    "email": {
      "type": [
        "string"
      ]
    },
    "employee": {
      "type": [
        "varies"
      ]
    },
    "employeeTaxList": {
      "type": [
        "varies"
      ]
    },
    "endDate": {
      "type": [
        "date-time"
      ]
    },
    "endOperation": {
      "type": [
        "varies"
      ]
    },
    "entity": {
      "type": [
        "varies"
      ]
    },
    "entityStatus": {
      "type": [
        "varies"
      ]
    },
    "entityTaxRegNum": {
      "type": [
        "varies"
      ]
    },
    "entryNumberUps": {
      "type": [
        "string"
      ]
    },
    "estGrossProfit": {
      "type": [
        "number",
        " string"
      ]
    },
    "estGrossProfitPercent": {
      "type": [
        "number",
        " string"
      ]
    },
    "estimatedTotalValue": {
      "type": [
        "number",
        " string"
      ]
    },
    "exchangeRate": {
      "type": [
        "number",
        " string"
      ]
    },
    "excludeCommission": {
      "type": [
        "boolean",
        " string"
      ]
    },
    "expCostDiscAmount": {
      "type": [
        "number",
        " string"
      ]
    },
    "expCostDiscPrint": {
      "type": [
        "boolean",
        " string"
      ]
    },
    "expCostDiscRate": {
      "type": [
        "string"
      ]
    },
    "expCostDiscTax1Amt": {
      "type": [
        "number",
        " string"
      ]
    },
    "expCostDiscTaxable": {
      "type": [
        "boolean",
        " string"
      ]
    },
    "expCostDiscount": {
      "type": [
        "varies"
      ]
    },
    "expCostDiscprint": {
      "type": [
        "boolean",
        " string"
      ]
    },
    "expCostList": {
      "type": [
        "varies"
      ]
    },
    "expCostTaxCode": {
      "type": [
        "varies"
      ]
    },
    "expCostTaxRate1": {
      "type": [
        "number",
        " string"
      ]
    },
    "expCostTaxRate2": {
      "type": [
        "number",
        " string"
      ]
    },
    "expandAssembly": {
      "type": [
        "boolean",
        " string"
      ]
    },
    "expectedCloseDate": {
      "type": [
        "date-time"
      ]
    },
    "expenseList": {
      "type": [
        "varies"
      ]
    },
    "expirationDate": {
      "type": [
        "date-time"
      ]
    },
    "exportTypeUps": {
      "type": [
        "varies"
      ]
    },
    "externalId": {
      "type": [
        "string"
      ]
    },
    "fax": {
      "type": [
        "string"
      ]
    },
    "firmed": {
      "type": [
        "boolean",
        " string"
      ]
    },
    "fob": {
      "type": [
        "string"
      ]
    },
    "forecastType": {
      "type": [
        "varies"
      ]
    },
    "fxAccount": {
      "type": [
        "varies"
      ]
    },
    "generateIntegratedShipperLabel": {
      "type": [
        "boolean",
        " string"
      ]
    },
    "getAuth": {
      "type": [
        "boolean",
        " string"
      ]
    },
    "giftCert": {
      "type": [
        "varies"
      ]
    },
    "giftCertApplied": {
      "type": [
        "number",
        " string"
      ]
    },
    "giftCertAvailable": {
      "type": [
        "number",
        " string"
      ]
    },
    "giftCertRedemptionList": {
      "type": [
        "varies"
      ]
    },
    "giftCertTotal": {
      "type": [
        "number",
        " string"
      ]
    },
    "halAddr1FedEx": {
      "type": [
        "string"
      ]
    },
    "halAddr2FedEx": {
      "type": [
        "string"
      ]
    },
    "halAddr3FedEx": {
      "type": [
        "string"
      ]
    },
    "halCityFedEx": {
      "type": [
        "string"
      ]
    },
    "halCountryFedEx": {
      "type": [
        "string"
      ]
    },
    "halPhoneFedEx": {
      "type": [
        "string"
      ]
    },
    "halStateFedEx": {
      "type": [
        "string"
      ]
    },
    "halZipFedEx": {
      "type": [
        "string"
      ]
    },
    "handlingCost": {
      "type": [
        "number",
        " string"
      ]
    },
    "handlingTax1Rate": {
      "type": [
        "number",
        " string"
      ]
    },
    "handlingTax2Rate": {
      "type": [
        "number",
        " string"
      ]
    },
    "handlingTaxCode": {
      "type": [
        "varies"
      ]
    },
    "hazmatTypeFedEx": {
      "type": [
        "varies"
      ]
    },
    "holdAtLocationFedEx": {
      "type": [
        "boolean",
        " string"
      ]
    },
    "homeDeliveryDateFedEx": {
      "type": [
        "date-time"
      ]
    },
    "homeDeliveryTypeFedEx": {
      "type": [
        "varies"
      ]
    },
    "ignoreAvs": {
      "type": [
        "boolean",
        " string"
      ]
    },
    "inbondCodeUps": {
      "type": [
        "string"
      ]
    },
    "inboundShipment": {
      "type": [
        "varies"
      ]
    },
    "includeInForecast": {
      "type": [
        "boolean",
        " string"
      ]
    },
    "incoterm": {
      "type": [
        "varies"
      ]
    },
    "insideDeliveryFedEx": {
      "type": [
        "boolean",
        " string"
      ]
    },
    "insidePickupFedEx": {
      "type": [
        "boolean",
        " string"
      ]
    },
    "intercoStatus": {
      "type": [
        "varies"
      ]
    },
    "intercoTransaction": {
      "type": [
        "varies"
      ]
    },
    "internalId": {
      "type": [
        "string"
      ]
    },
    "intlExemptionNumFedEx": {
      "type": [
        "string"
      ]
    },
    "inventoryDetail": {
      "type": [
        "varies"
      ]
    },
    "inventoryList": {
      "type": [
        "varies"
      ]
    },
    "inventoryValue": {
      "type": [
        "number",
        " string"
      ]
    },
    "isBackflush": {
      "type": [
        "boolean",
        " string"
      ]
    },
    "isBookSpecific": {
      "type": [
        "boolean",
        " string"
      ]
    },
    "isCargoAircraftOnlyFedEx": {
      "type": [
        "boolean",
        " string"
      ]
    },
    "isMultiShipTo": {
      "type": [
        "boolean",
        " string"
      ]
    },
    "isRecurringPayment": {
      "type": [
        "boolean",
        " string"
      ]
    },
    "isRoutedExportTransactionUps": {
      "type": [
        "boolean",
        " string"
      ]
    },
    "isTaxable": {
      "type": [
        "boolean",
        " string"
      ]
    },
    "isWip": {
      "type": [
        "boolean",
        " string"
      ]
    },
    "item": {
      "type": [
        "varies"
      ]
    },
    "itemCostDiscAmount": {
      "type": [
        "number",
        " string"
      ]
    },
    "itemCostDiscPrint": {
      "type": [
        "boolean",
        " string"
      ]
    },
    "itemCostDiscRate": {
      "type": [
        "string"
      ]
    },
    "itemCostDiscTax1Amt": {
      "type": [
        "number",
        " string"
      ]
    },
    "itemCostDiscTaxable": {
      "type": [
        "boolean",
        " string"
      ]
    },
    "itemCostDiscount": {
      "type": [
        "varies"
      ]
    },
    "itemCostList": {
      "type": [
        "varies"
      ]
    },
    "itemCostTaxCode": {
      "type": [
        "varies"
      ]
    },
    "itemCostTaxRate1": {
      "type": [
        "number",
        " string"
      ]
    },
    "itemCostTaxRate2": {
      "type": [
        "number",
        " string"
      ]
    },
    "itemFulfillment": {
      "type": [
        "varies"
      ]
    },
    "itemList": {
      "type": [
        "varies"
      ]
    },
    "job": {
      "type": [
        "varies"
      ]
    },
    "landedCostMethod": {
      "type": [
        "varies"
      ]
    },
    "landedCostPerLine": {
      "type": [
        "boolean",
        " string"
      ]
    },
    "landedCostsList": {
      "type": [
        "varies"
      ]
    },
    "lastModifiedDate": {
      "type": [
        "date-time"
      ]
    },
    "leadSource": {
      "type": [
        "varies"
      ]
    },
    "licenseDateUps": {
      "type": [
        "date-time"
      ]
    },
    "licenseExceptionUps": {
      "type": [
        "varies"
      ]
    },
    "licenseNumberUps": {
      "type": [
        "string"
      ]
    },
    "lineList": {
      "type": [
        "varies"
      ]
    },
    "linkedTrackingNumbers": {
      "type": [
        "string"
      ]
    },
    "location": {
      "type": [
        "varies"
      ]
    },
    "manufacturingRouting": {
      "type": [
        "varies"
      ]
    },
    "memo": {
      "type": [
        "string"
      ]
    },
    "message": {
      "type": [
        "string"
      ]
    },
    "messageSel": {
      "type": [
        "varies"
      ]
    },
    "methodOfTransportUps": {
      "type": [
        "varies"
      ]
    },
    "nextApprover": {
      "type": [
        "varies"
      ]
    },
    "nextBill": {
      "type": [
        "date-time"
      ]
    },
    "nexus": {
      "type": [
        "varies"
      ]
    },
    "nullFieldList": {
      "type": [
        "varies"
      ]
    },
    "onCreditHold": {
      "type": [
        "string"
      ]
    },
    "oneTime": {
      "type": [
        "number",
        " string"
      ]
    },
    "operationList": {
      "type": [
        "varies"
      ]
    },
    "opportunity": {
      "type": [
        "varies"
      ]
    },
    "options": {
      "type": [
        "varies"
      ]
    },
    "orderQuantity": {
      "type": [
        "number",
        " string"
      ]
    },
    "orderStatus": {
      "type": [
        "varies"
      ]
    },
    "otherList": {
      "type": [
        "varies"
      ]
    },
    "otherRefNum": {
      "type": [
        "string"
      ]
    },
    "packageFedExList": {
      "type": [
        "varies"
      ]
    },
    "packageList": {
      "type": [
        "varies"
      ]
    },
    "packageUpsList": {
      "type": [
        "varies"
      ]
    },
    "packageUspsList": {
      "type": [
        "varies"
      ]
    },
    "packedDate": {
      "type": [
        "date-time"
      ]
    },
    "parentExpenseAlloc": {
      "type": [
        "varies"
      ]
    },
    "partiesToTransactionUps": {
      "type": [
        "boolean",
        " string"
      ]
    },
    "partner": {
      "type": [
        "varies"
      ]
    },
    "partnersList": {
      "type": [
        "varies"
      ]
    },
    "payPalStatus": {
      "type": [
        "string"
      ]
    },
    "payPalTranId": {
      "type": [
        "string"
      ]
    },
    "payment": {
      "type": [
        "number",
        " string"
      ]
    },
    "paymentEventDate": {
      "type": [
        "date-time"
      ]
    },
    "paymentEventHoldReason": {
      "type": [
        "varies"
      ]
    },
    "paymentEventResult": {
      "type": [
        "varies"
      ]
    },
    "paymentEventType": {
      "type": [
        "varies"
      ]
    },
    "paymentEventUpdatedBy": {
      "type": [
        "string"
      ]
    },
    "paymentHold": {
      "type": [
        "boolean",
        " string"
      ]
    },
    "paymentList": {
      "type": [
        "varies"
      ]
    },
    "paymentMethod": {
      "type": [
        "varies"
      ]
    },
    "paypalAuthId": {
      "type": [
        "string"
      ]
    },
    "paypalProcess": {
      "type": [
        "boolean",
        " string"
      ]
    },
    "pending": {
      "type": [
        "number",
        " string"
      ]
    },
    "pickedDate": {
      "type": [
        "date-time"
      ]
    },
    "pnRefNum": {
      "type": [
        "string"
      ]
    },
    "postingPeriod": {
      "type": [
        "varies"
      ]
    },
    "printVoucher": {
      "type": [
        "boolean",
        " string"
      ]
    },
    "probability": {
      "type": [
        "number",
        " string"
      ]
    },
    "promoCode": {
      "type": [
        "varies"
      ]
    },
    "promotionsList": {
      "type": [
        "varies"
      ]
    },
    "purchaseContract": {
      "type": [
        "varies"
      ]
    },
    "purchaseOrderList": {
      "type": [
        "varies"
      ]
    },
    "quantity": {
      "type": [
        "number",
        " string"
      ]
    },
    "recipientTaxIdUps": {
      "type": [
        "string"
      ]
    },
    "recognizedRevenue": {
      "type": [
        "number",
        " string"
      ]
    },
    "recurAnnually": {
      "type": [
        "number",
        " string"
      ]
    },
    "recurMonthly": {
      "type": [
        "number",
        " string"
      ]
    },
    "recurQuarterly": {
      "type": [
        "number",
        " string"
      ]
    },
    "recurWeekly": {
      "type": [
        "number",
        " string"
      ]
    },
    "recurringBill": {
      "type": [
        "boolean",
        " string"
      ]
    },
    "refundCheck": {
      "type": [
        "boolean",
        " string"
      ]
    },
    "requestedBy": {
      "type": [
        "varies"
      ]
    },
    "revCommitStatus": {
      "type": [
        "varies"
      ]
    },
    "revRecEndDate": {
      "type": [
        "date-time"
      ]
    },
    "revRecOnRevCommitment": {
      "type": [
        "boolean",
        " string"
      ]
    },
    "revRecSchedule": {
      "type": [
        "varies"
      ]
    },
    "revRecStartDate": {
      "type": [
        "date-time"
      ]
    },
    "revenueStatus": {
      "type": [
        "varies"
      ]
    },
    "reversalDate": {
      "type": [
        "date-time"
      ]
    },
    "reversalDefer": {
      "type": [
        "boolean",
        " string"
      ]
    },
    "reversalEntry": {
      "type": [
        "string"
      ]
    },
    "revision": {
      "type": [
        "varies"
      ]
    },
    "salesEffectiveDate": {
      "type": [
        "date-time"
      ]
    },
    "salesGroup": {
      "type": [
        "varies"
      ]
    },
    "salesOrder": {
      "type": [
        "varies"
      ]
    },
    "salesRep": {
      "type": [
        "varies"
      ]
    },
    "salesTeamList": {
      "type": [
        "varies"
      ]
    },
    "saturdayDeliveryFedEx": {
      "type": [
        "boolean",
        " string"
      ]
    },
    "saturdayDeliveryUps": {
      "type": [
        "boolean",
        " string"
      ]
    },
    "saturdayPickupFedex": {
      "type": [
        "boolean",
        " string"
      ]
    },
    "saveOnAuthDecline": {
      "type": [
        "boolean",
        " string"
      ]
    },
    "schedulingMethod": {
      "type": [
        "varies"
      ]
    },
    "scrapQuantity": {
      "type": [
        "number",
        " string"
      ]
    },
    "sendBackupEmailFedEx": {
      "type": [
        "boolean",
        " string"
      ]
    },
    "sendBackupEmailUps": {
      "type": [
        "boolean",
        " string"
      ]
    },
    "sendShipNotifyEmailFedEx": {
      "type": [
        "boolean",
        " string"
      ]
    },
    "sendShipNotifyEmailUps": {
      "type": [
        "boolean",
        " string"
      ]
    },
    "serialNumbers": {
      "type": [
        "string"
      ]
    },
    "shipAddress": {
      "type": [
        "string"
      ]
    },
    "shipAddressList": {
      "type": [
        "varies"
      ]
    },
    "shipComplete": {
      "type": [
        "boolean",
        " string"
      ]
    },
    "shipDate": {
      "type": [
        "date-time"
      ]
    },
    "shipDateFedEx": {
      "type": [
        "date-time"
      ]
    },
    "shipGroupList": {
      "type": [
        "varies"
      ]
    },
    "shipIsResidential": {
      "type": [
        "boolean",
        " string"
      ]
    },
    "shipMethod": {
      "type": [
        "varies"
      ]
    },
    "shipNotifyEmailAddress2Ups": {
      "type": [
        "string"
      ]
    },
    "shipNotifyEmailAddressFedEx": {
      "type": [
        "string"
      ]
    },
    "shipNotifyEmailAddressUps": {
      "type": [
        "string"
      ]
    },
    "shipNotifyEmailMessageUps": {
      "type": [
        "string"
      ]
    },
    "shipStatus": {
      "type": [
        "varies"
      ]
    },
    "shipTo": {
      "type": [
        "varies"
      ]
    },
    "shipmentWeightFedEx": {
      "type": [
        "number",
        " string"
      ]
    },
    "shipmentWeightUps": {
      "type": [
        "number",
        " string"
      ]
    },
    "shippedDate": {
      "type": [
        "date-time"
      ]
    },
    "shippingAddress": {
      "type": [
        "varies"
      ]
    },
    "shippingCost": {
      "type": [
        "number",
        " string"
      ]
    },
    "shippingTax1Rate": {
      "type": [
        "number",
        " string"
      ]
    },
    "shippingTax2Rate": {
      "type": [
        "number",
        " string"
      ]
    },
    "shippingTaxCode": {
      "type": [
        "varies"
      ]
    },
    "shopperIpAddress": {
      "type": [
        "string"
      ]
    },
    "signatureHomeDeliveryFedEx": {
      "type": [
        "boolean",
        " string"
      ]
    },
    "softDescriptor": {
      "type": [
        "string"
      ]
    },
    "source": {
      "type": [
        "string"
      ]
    },
    "sourceTransactionId": {
      "type": [
        "string"
      ]
    },
    "sourceTransactionLine": {
      "type": [
        "integer",
        " string"
      ]
    },
    "specialOrder": {
      "type": [
        "boolean",
        " string"
      ]
    },
    "startDate": {
      "type": [
        "date-time"
      ]
    },
    "startOperation": {
      "type": [
        "varies"
      ]
    },
    "status": {
      "type": [
        "string"
      ]
    },
    "subTotal": {
      "type": [
        "number",
        " string"
      ]
    },
    "subsidiary": {
      "type": [
        "varies"
      ]
    },
    "subsidiaryTaxRegNum": {
      "type": [
        "varies"
      ]
    },
    "supervisorApproval": {
      "type": [
        "boolean",
        " string"
      ]
    },
    "syncPartnerTeams": {
      "type": [
        "boolean",
        " string"
      ]
    },
    "syncSalesTeams": {
      "type": [
        "boolean",
        " string"
      ]
    },
    "tax1Amt": {
      "type": [
        "number",
        " string"
      ]
    },
    "tax2Amt": {
      "type": [
        "number",
        " string"
      ]
    },
    "tax2Total": {
      "type": [
        "number",
        " string"
      ]
    },
    "taxDetailsList": {
      "type": [
        "varies"
      ]
    },
    "taxDetailsOverride": {
      "type": [
        "boolean",
        " string"
      ]
    },
    "taxItem": {
      "type": [
        "varies"
      ]
    },
    "taxRate": {
      "type": [
        "number",
        " string"
      ]
    },
    "taxRegOverride": {
      "type": [
        "boolean",
        " string"
      ]
    },
    "taxTotal": {
      "type": [
        "number",
        " string"
      ]
    },
    "terms": {
      "type": [
        "varies"
      ]
    },
    "termsFreightChargeFedEx": {
      "type": [
        "number",
        " string"
      ]
    },
    "termsInsuranceChargeFedEx": {
      "type": [
        "number",
        " string"
      ]
    },
    "termsOfSaleFedEx": {
      "type": [
        "varies"
      ]
    },
    "thirdPartyAcctFedEx": {
      "type": [
        "string"
      ]
    },
    "thirdPartyAcctUps": {
      "type": [
        "string"
      ]
    },
    "thirdPartyCountryFedEx": {
      "type": [
        "varies"
      ]
    },
    "thirdPartyCountryUps": {
      "type": [
        "varies"
      ]
    },
    "thirdPartyTypeFedEx": {
      "type": [
        "varies"
      ]
    },
    "thirdPartyTypeUps": {
      "type": [
        "varies"
      ]
    },
    "thirdPartyZipcodeUps": {
      "type": [
        "string"
      ]
    },
    "threeDStatusCode": {
      "type": [
        "string"
      ]
    },
    "timeDiscAmount": {
      "type": [
        "number",
        " string"
      ]
    },
    "timeDiscPrint": {
      "type": [
        "boolean",
        " string"
      ]
    },
    "timeDiscRate": {
      "type": [
        "string"
      ]
    },
    "timeDiscTax1Amt": {
      "type": [
        "number",
        " string"
      ]
    },
    "timeDiscTaxable": {
      "type": [
        "boolean",
        " string"
      ]
    },
    "timeDiscount": {
      "type": [
        "varies"
      ]
    },
    "timeList": {
      "type": [
        "varies"
      ]
    },
    "timeTaxCode": {
      "type": [
        "varies"
      ]
    },
    "timeTaxRate1": {
      "type": [
        "number",
        " string"
      ]
    },
    "timeTaxRate2": {
      "type": [
        "number",
        " string"
      ]
    },
    "title": {
      "type": [
        "string"
      ]
    },
    "toAch": {
      "type": [
        "boolean",
        " string"
      ]
    },
    "toBeEmailed": {
      "type": [
        "boolean",
        " string"
      ]
    },
    "toBeFaxed": {
      "type": [
        "boolean",
        " string"
      ]
    },
    "toBePrinted": {
      "type": [
        "boolean",
        " string"
      ]
    },
    "toPrint2": {
      "type": [
        "boolean",
        " string"
      ]
    },
    "toSubsidiary": {
      "type": [
        "varies"
      ]
    },
    "total": {
      "type": [
        "number",
        " string"
      ]
    },
    "totalCostEstimate": {
      "type": [
        "number",
        " string"
      ]
    },
    "trackingNumbers": {
      "type": [
        "string"
      ]
    },
    "tranDate": {
      "type": [
        "date-time"
      ]
    },
    "tranId": {
      "type": [
        "string"
      ]
    },
    "tranIsVsoeBundle": {
      "type": [
        "boolean",
        " string"
      ]
    },
    "transactionNumber": {
      "type": [
        "string"
      ]
    },
    "transferLocation": {
      "type": [
        "varies"
      ]
    },
    "unapplied": {
      "type": [
        "number",
        " string"
      ]
    },
    "undepFunds": {
      "type": [
        "boolean",
        " string"
      ]
    },
    "unitCost": {
      "type": [
        "number",
        " string"
      ]
    },
    "units": {
      "type": [
        "varies"
      ]
    },
    "unitsType": {
      "type": [
        "varies"
      ]
    },
    "useItemCostAsTransferCost": {
      "type": [
        "boolean",
        " string"
      ]
    },
    "useMultiCurrency": {
      "type": [
        "boolean",
        " string"
      ]
    },
    "userTaxTotal": {
      "type": [
        "number",
        " string"
      ]
    },
    "userTotal": {
      "type": [
        "number",
        " string"
      ]
    },
    "validFrom": {
      "type": [
        "date-time"
      ]
    },
    "vatRegNum": {
      "type": [
        "string"
      ]
    },
    "visibleToCustomer": {
      "type": [
        "boolean",
        " string"
      ]
    },
    "voidJournal": {
      "type": [
        "varies"
      ]
    },
    "vsoeAutoCalc": {
      "type": [
        "boolean",
        " string"
      ]
    }
  }
}