{
  "properties": {
    "calculated_at": {
      "type": [
        "null",
        "date-time"
      ]
    },
    "catalog_object_id": {
      "type": [
        "null",
        "string"
      ]
    },
    "catalog_object_type": {
      "type": [
        "null",
        "string"
      ]
    },
    "location_id": {
      "type": [
        "null",
        "string"
      ]
    },
    "quantity": {
      "type": [
        "null",
        "string"
      ]
    },
    "state": {
      "type": [
        "null",
        "string"
      ]
    }
  },
  "type": [
    "null",
    "object"
  ]
}