{
  "type": "object",
  "additionalProperties": false,
  "properties": {
    "name": {
      "type": [
        "null",
        "string"
      ]
    },
    "account_url": {
      "type": [
        "null",
        "string"
      ]
    },
    "created_timestamp": {
      "type": [
        "null",
        "date-time"
      ]
    },
    "updated_timestamp": {
      "type": [
        "null",
        "date-time"
      ]
    },
    "contact_count": {
      "type": [
        "null",
        "integer"
      ]
    },
    "deal_count": {
      "type": [
        "null",
        "integer"
      ]
    },
    "id": {
      "type": [
        "null",
        "integer"
      ]
    }
  }
}