{
  "additionalProperties": false,
  "properties": {
    "address1": {
      "type": [
        "null",
        "string"
      ]
    },
    "address2": {
      "type": [
        "null",
        "string"
      ]
    },
    "allgroup": {
      "type": [
        "null",
        "integer"
      ]
    },
    "city": {
      "type": [
        "null",
        "string"
      ]
    },
    "company_name": {
      "type": [
        "null",
        "string"
      ]
    },
    "country": {
      "type": [
        "null",
        "string"
      ]
    },
    "district": {
      "type": [
        "null",
        "string"
      ]
    },
    "id": {
      "type": [
        "null",
        "integer"
      ]
    },
    "is_default": {
      "type": [
        "null",
        "boolean"
      ]
    },
    "state": {
      "type": [
        "null",
        "string"
      ]
    },
    "zip": {
      "type": [
        "null",
        "string"
      ]
    }
  },
  "type": "object"
}