{
  "properties": {
    "account_arrears_settings": {
      "properties": {
        "date_calculation_method": {
          "type": [
            "string"
          ]
        },
        "encoded_key": {
          "type": [
            "string"
          ]
        },
        "monthly_tolerance_day": {
          "type": [
            "integer"
          ]
        },
        "non_working_days_method": {
          "type": [
            "string"
          ]
        },
        "tolerance_calculation_method": {
          "type": [
            "string"
          ]
        },
        "tolerance_period": {
          "type": [
            "integer"
          ]
        }
      },
      "type": [
        "object"
      ]
    },
    "account_holder_key": {
      "type": [
        "string"
      ]
    },
    "account_holder_type": {
      "type": [
        "string"
      ]
    },
    "account_state": {
      "type": [
        "string"
      ]
    },
    "account_sub_state": {
      "type": [
        "string"
      ]
    },
    "accrued_interest": {
      "type": [
        "number"
      ]
    },
    "accrued_penalty": {
      "type": [
        "number"
      ]
    },
    "activation_transaction_key": {
      "type": [
        "string"
      ]
    },
    "allow_offset": {
      "type": [
        "boolean"
      ]
    },
    "approved_date": {
      "type": [
        "date-time"
      ]
    },
    "arrears_tolerance_period": {
      "type": [
        "integer"
      ]
    },
    "assets": {
      "properties": {
        "amount": {
          "type": [
            "number"
          ]
        },
        "assetName": {
          "type": [
            "string"
          ]
        },
        "depositAccountKey": {
          "type": [
            "string"
          ]
        },
        "encodedKey": {
          "type": [
            "string"
          ]
        },
        "guarantorKey": {
          "type": [
            "string"
          ]
        },
        "guarantorType": {
          "type": [
            "string"
          ]
        }
      },
      "type": [
        "array"
      ]
    },
    "assigned_branch_key": {
      "type": [
        "string"
      ]
    },
    "assigned_centre_key": {
      "type": [
        "string"
      ]
    },
    "assigned_user_key": {
      "type": [
        "string"
      ]
    },
    "balances": {
      "properties": {
        "fees_balance": {
          "type": [
            "number"
          ]
        },
        "fees_due": {
          "type": [
            "number"
          ]
        },
        "fees_paid": {
          "type": [
            "number"
          ]
        },
        "interest_balance": {
          "type": [
            "number"
          ]
        },
        "interest_due": {
          "type": [
            "number"
          ]
        },
        "interest_from_arrears_balance": {
          "type": [
            "number"
          ]
        },
        "interest_from_arrears_due": {
          "type": [
            "number"
          ]
        },
        "interest_from_arrears_paid": {
          "type": [
            "number"
          ]
        },
        "interest_paid": {
          "type": [
            "number"
          ]
        },
        "penalty_balance": {
          "type": [
            "number"
          ]
        },
        "penalty_due": {
          "type": [
            "number"
          ]
        },
        "penalty_paid": {
          "type": [
            "number"
          ]
        },
        "principal_balance": {
          "type": [
            "number"
          ]
        },
        "principal_due": {
          "type": [
            "number"
          ]
        },
        "principal_paid": {
          "type": [
            "number"
          ]
        },
        "redraw_balance": {
          "type": [
            "number"
          ]
        }
      },
      "type": [
        "object"
      ]
    },
    "closed_date": {
      "type": [
        "date-time"
      ]
    },
    "creation_date": {
      "type": [
        "date-time"
      ]
    },
    "credit_arrangement_key": {
      "type": [
        "string"
      ]
    },
    "custom_fields": {
      "properties": {
        "field_set_id": {
          "type": [
            "string"
          ]
        },
        "id": {
          "type": [
            "string"
          ]
        },
        "value": {
          "type": [
            "string"
          ]
        }
      },
      "type": [
        "array"
      ]
    },
    "days_in_arrears": {
      "type": [
        "integer"
      ]
    },
    "days_late": {
      "type": [
        "integer"
      ]
    },
    "disbursement_details": {
      "properties": {
        "disbursement_date": {
          "type": [
            "date-time"
          ]
        },
        "encoded_key": {
          "type": [
            "string"
          ]
        },
        "expected_disbursement_date": {
          "type": [
            "date-time"
          ]
        },
        "fees": {
          "properties": {
            "amount": {
              "type": [
                "integer"
              ]
            },
            "encoded_key": {
              "type": [
                "string"
              ]
            },
            "predefined_fee_encoded_key": {
              "type": [
                "string"
              ]
            }
          },
          "type": [
            "array"
          ]
        },
        "first_repayment_date": {
          "type": [
            "date-time"
          ]
        },
        "transaction_details": {
          "properties": {
            "encoded_key": {
              "type": [
                "string"
              ]
            },
            "internal_transfer": {
              "type": [
                "boolean"
              ]
            },
            "target_deposit_account_key": {
              "type": [
                "string"
              ]
            },
            "transaction_channel_id": {
              "type": [
                "string"
              ]
            },
            "transaction_channel_key": {
              "type": [
                "string"
              ]
            }
          },
          "type": [
            "object"
          ]
        }
      },
      "type": [
        "object"
      ]
    },
    "encoded_key": {
      "type": [
        "string"
      ]
    },
    "funding_sources": {
      "properties": {
        "amount": {
          "type": [
            "number"
          ]
        },
        "asset_name": {
          "type": [
            "string"
          ]
        },
        "deposit_account_key": {
          "type": [
            "string"
          ]
        },
        "encoded_key": {
          "type": [
            "string"
          ]
        },
        "guarantor_key": {
          "type": [
            "string"
          ]
        },
        "id": {
          "type": [
            "string"
          ]
        },
        "interest_commission": {
          "type": [
            "integer"
          ]
        },
        "share_percentage": {
          "type": [
            "number"
          ]
        }
      },
      "type": [
        "array"
      ]
    },
    "future_payments_acceptance": {
      "type": [
        "string"
      ]
    },
    "guarantors": {
      "properties": {
        "amount": {
          "type": [
            "number"
          ]
        },
        "asset_name": {
          "type": [
            "string"
          ]
        },
        "deposit_account_key": {
          "type": [
            "string"
          ]
        },
        "encoded_key": {
          "type": [
            "string"
          ]
        },
        "guarantor_key": {
          "type": [
            "string"
          ]
        },
        "guarantor_type": {
          "type": [
            "string"
          ]
        }
      },
      "type": [
        "array"
      ]
    },
    "id": {
      "type": [
        "string"
      ]
    },
    "interest_commission": {
      "type": [
        "number"
      ]
    },
    "interest_from_arrears_accrued": {
      "type": [
        "number"
      ]
    },
    "interest_settings": {
      "properties": {
        "accrue_interest_after_maturity": {
          "type": [
            "boolean"
          ]
        },
        "interest_application_method": {
          "type": [
            "string"
          ]
        },
        "interest_balance_calculation_method": {
          "type": [
            "string"
          ]
        },
        "interest_calculation_method": {
          "type": [
            "string"
          ]
        },
        "interest_charge_frequency": {
          "type": [
            "string"
          ]
        },
        "interest_rate": {
          "type": [
            "number"
          ]
        },
        "interest_rate_review_count": {
          "type": [
            "integer"
          ]
        },
        "interest_rate_review_unit": {
          "type": [
            "string"
          ]
        },
        "interest_rate_source": {
          "type": [
            "string"
          ]
        },
        "interest_spread": {
          "type": [
            "number"
          ]
        },
        "interest_type": {
          "type": [
            "string"
          ]
        }
      },
      "type": [
        "object"
      ]
    },
    "last_appraisal_date": {
      "type": [
        "date-time"
      ]
    },
    "last_interest_applied_date": {
      "type": [
        "date-time"
      ]
    },
    "last_interest_review_date": {
      "type": [
        "date-time"
      ]
    },
    "last_locked_date": {
      "type": [
        "date-time"
      ]
    },
    "last_modified_date": {
      "type": [
        "date-time"
      ]
    },
    "last_sent_to_arrears_date": {
      "type": [
        "date-time"
      ]
    },
    "last_tax_rate_review_date": {
      "type": [
        "date-time"
      ]
    },
    "late_payments_recalculation_method": {
      "type": [
        "string"
      ]
    },
    "loan_amount": {
      "type": [
        "number"
      ]
    },
    "loan_name": {
      "type": [
        "string"
      ]
    },
    "locked_operations": {
      "properties": {
        "value": {
          "type": [
            "string"
          ]
        }
      },
      "type": [
        "array"
      ]
    },
    "migration_event_key": {
      "type": [
        "string"
      ]
    },
    "notes": {
      "type": [
        "string"
      ]
    },
    "original_account_key": {
      "type": [
        "string"
      ]
    },
    "payment_method": {
      "type": [
        "string"
      ]
    },
    "penalty_settings": {
      "properties": {
        "loan_penalty_calculation_method": {
          "type": [
            "string"
          ]
        },
        "penalty_rate": {
          "type": [
            "number"
          ]
        }
      },
      "type": [
        "object"
      ]
    },
    "prepayment_settings": {
      "properties": {
        "apply_interest_on_prepayment_method": {
          "type": [
            "string"
          ]
        },
        "elements_recalculation_method": {
          "type": [
            "string"
          ]
        },
        "prepayment_recalculation_method": {
          "type": [
            "string"
          ]
        },
        "principal-paid_installment_status": {
          "type": [
            "string"
          ]
        }
      },
      "type": [
        "object"
      ]
    },
    "principal_payment_settings": {
      "properties": {
        "amount": {
          "type": [
            "number"
          ]
        },
        "encoded_key": {
          "type": [
            "string"
          ]
        },
        "include_fees_in_floor_amount": {
          "type": [
            "boolean"
          ]
        },
        "include_interest_in_floor_amount": {
          "type": [
            "boolean"
          ]
        },
        "percentage": {
          "type": [
            "number"
          ]
        },
        "principal_ceiling_value": {
          "type": [
            "number"
          ]
        },
        "principal_floor_value": {
          "type": [
            "number"
          ]
        },
        "principal_payment_method": {
          "type": [
            "string"
          ]
        },
        "total_due_amount_floor": {
          "type": [
            "number"
          ]
        },
        "total_due_payment": {
          "type": [
            "string"
          ]
        }
      },
      "type": [
        "object"
      ]
    },
    "product_type_key": {
      "type": [
        "string"
      ]
    },
    "rescheduled_account_key": {
      "type": [
        "string"
      ]
    },
    "schedule_settings": {
      "properties": {
        "default_first_repayment_due_date_offset": {
          "type": [
            "integer"
          ]
        },
        "fixed_days_of_month": {
          "properties": {
            "value": {
              "type": [
                "integer"
              ]
            }
          },
          "type": [
            "array"
          ]
        },
        "grace_period": {
          "type": [
            "integer"
          ]
        },
        "grace_period_type": {
          "type": [
            "string"
          ]
        },
        "has_custom_schedule": {
          "type": [
            "boolean"
          ]
        },
        "payment_plan": {
          "properties": {
            "amount": {
              "type": [
                "number"
              ]
            },
            "encoded_key": {
              "type": [
                "string"
              ]
            },
            "to_installment": {
              "type": [
                "integer"
              ]
            }
          },
          "type": [
            "array"
          ]
        },
        "periodic_payment": {
          "type": [
            "number"
          ]
        },
        "principal_repayment_interval": {
          "type": [
            "integer"
          ]
        },
        "repayment_installments": {
          "type": [
            "integer"
          ]
        },
        "repayment_period_count": {
          "type": [
            "integer"
          ]
        },
        "repayment_period_unit": {
          "type": [
            "string"
          ]
        },
        "repayment_schedule_method": {
          "type": [
            "string"
          ]
        },
        "schedule_due_dates_method": {
          "type": [
            "string"
          ]
        },
        "short_month_handling_method": {
          "type": [
            "string"
          ]
        }
      },
      "type": [
        "object"
      ]
    },
    "settlement_account_key": {
      "type": [
        "string"
      ]
    },
    "tax_rate": {
      "type": [
        "number"
      ]
    },
    "tranches": {
      "properties": {
        "amount": {
          "type": [
            "number"
          ]
        },
        "disbursement_details": {
          "properties": {
            "disbursement_transaction_key": {
              "type": [
                "string"
              ]
            },
            "expected_disbursement_date": {
              "type": [
                "date-time"
              ]
            }
          },
          "type": [
            "object"
          ]
        },
        "encoded_key": {
          "type": [
            "string"
          ]
        },
        "tranch_number": {
          "type": [
            "string"
          ]
        }
      },
      "type": [
        "array"
      ]
    }
  }
}