{
  "properties": {
    "CategoryID": {
      "description": "Specifies the identifier of the folder containing the email.",
      "type": [
        "null",
        "integer"
      ]
    },
    "CharacterSet": {
      "description": "Indicates encoding used in an email message.",
      "type": [
        "null",
        "string"
      ]
    },
    "ClonedFromID": {
      "description": "ID of email message from which the specified email message was created.",
      "type": [
        "null",
        "integer"
      ]
    },
    "ContentAreaIDs": {
      "description": "Contains information on content areas included in an email message.",
      "items": {
        "type": [
          "null",
          "integer"
        ]
      },
      "type": "array"
    },
    "ContentCheckStatus": {
      "description": "Indicates whether content validation has completed for this email message.",
      "type": [
        "null",
        "string"
      ]
    },
    "CreatedDate": {
      "description": "Read-only date and time of the object's creation.",
      "type": [
        "null",
        "string"
      ]
    },
    "CustomerKey": {
      "description": "User-supplied unique identifier for an object within an object type (corresponds to the external key assigned to an object in the user interface).",
      "type": [
        "null",
        "string"
      ]
    },
    "EmailType": {
      "description": "Defines preferred email type.",
      "type": [
        "null",
        "string"
      ]
    },
    "HTMLBody": {
      "description": "Contains HTML body of an email message.",
      "type": [
        "null",
        "string"
      ]
    },
    "HasDynamicSubjectLine": {
      "description": "Indicates whether email message contains a dynamic subject line.",
      "type": [
        "null",
        "boolean"
      ]
    },
    "ID": {
      "description": "Read-only legacy identifier for an object. Not supported on all objects. Some objects use the ObjectID property as the Marketing Cloud unique ID.",
      "type": [
        "null",
        "integer"
      ]
    },
    "IsActive": {
      "description": "Specifies whether the object is active.",
      "type": [
        "null",
        "boolean"
      ]
    },
    "IsHTMLPaste": {
      "description": "Indicates whether email message was created via pasted HTML.",
      "type": [
        "null",
        "boolean"
      ]
    },
    "ModifiedDate": {
      "description": "Indicates the last time object information was modified.",
      "type": [
        "null",
        "string"
      ]
    },
    "Name": {
      "description": "Name of the object or property.",
      "type": [
        "null",
        "string"
      ]
    },
    "ObjectID": {
      "description": "System-controlled, read-only text string identifier for object.",
      "type": [
        "null",
        "string"
      ]
    },
    "PartnerProperties": {
      "description": "Specifies key-value pairs of properties associated with an object.",
      "items": {
        "properties": {
          "Name": {
            "type": [
              "null",
              "string"
            ]
          },
          "Value": {
            "type": [
              "null",
              "string"
            ]
          }
        },
        "type": "object"
      },
      "type": "array"
    },
    "PreHeader": {
      "description": "Contains text used in preheader of email message on mobile devices.",
      "type": [
        "null",
        "string"
      ]
    },
    "Status": {
      "description": "Defines status of object. Status of an address.",
      "type": [
        "null",
        "string"
      ]
    },
    "Subject": {
      "description": "Contains subject area information for a message.",
      "type": [
        "null",
        "string"
      ]
    },
    "SyncTextWithHTML": {
      "description": "Makes the text version of an email contain the same content as the HTML version.",
      "type": [
        "null",
        "boolean"
      ]
    },
    "TextBody": {
      "description": "Contains raw text body of a message.",
      "type": [
        "null",
        "string"
      ]
    },
    "__AdditionalEmailAttribute1": {
      "type": [
        "null",
        "string"
      ]
    },
    "__AdditionalEmailAttribute2": {
      "type": [
        "null",
        "string"
      ]
    },
    "__AdditionalEmailAttribute3": {
      "type": [
        "null",
        "string"
      ]
    },
    "__AdditionalEmailAttribute4": {
      "type": [
        "null",
        "string"
      ]
    },
    "__AdditionalEmailAttribute5": {
      "type": [
        "null",
        "string"
      ]
    }
  },
  "type": "object"
}