{
  "properties": {
    "BudgetEntryType": {
      "type": [
        "null",
        "string"
      ]
    },
    "Name": {
      "type": [
        "null",
        "string"
      ]
    },
    "domain": {
      "type": [
        "null",
        "string"
      ]
    },
    "Active": {
      "type": [
        "null",
        "boolean"
      ]
    },
    "EndDate": {
      "type": [
        "null",
        "date-time"
      ]
    },
    "StartDate": {
      "type": [
        "null",
        "date-time"
      ]
    },
    "BudgetType": {
      "type": [
        "null",
        "string"
      ]
    },
    "SyncToken": {
      "type": [
        "null",
        "string"
      ]
    },
    "Id": {
      "type": [
        "null",
        "string"
      ]
    },
    "BudgetDetail": {
      "items": {
        "properties": {
          "ClassRef": {
            "name": {
              "type": [
                "null",
                "string"
              ]
            },
            "value": {
              "type": [
                "null",
                "string"
              ]
            }
          },
          "DepartmentRef": {
            "name": {
              "type": [
                "null",
                "string"
              ]
            },
            "value": {
              "type": [
                "null",
                "string"
              ]
            }
          },
          "CustomerRef": {
            "name": {
              "type": [
                "null",
                "string"
              ]
            },
            "value": {
              "type": [
                "null",
                "string"
              ]
            }
          },
          "AccountRef": {
            "name": {
              "type": [
                "null",
                "string"
              ]
            },
            "value": {
              "type": [
                "null",
                "string"
              ]
            }
          },
          "BudgetDate": {
            "type": [
              "null",
              "date-time"
            ]
          },
          "Amount": {
            "type": [
              "null",
              "number"
            ]
          }
        },
        "type": [
          "null",
          "object"
        ]
      },
      "type": [
        "null",
        "array"
      ]
    },
    "MetaData": {
      "properties": {
        "CreateTime": {
          "type": [
            "null",
            "date-time"
          ]
        },
        "LastUpdatedTime": {
          "type": [
            "null",
            "date-time"
          ]
        }
      },
      "type": [
        "null",
        "object"
      ]
    }
  },
  "type": [
    "null",
    "object"
  ]
}