{
  "properties": {
    "HiredDate": {
      "type": [
        "null",
        "date-time"
      ]
    },
    "PrimaryPhone": {
      "properties": {
        "FreeFormNumber": {
          "type": [
            "null",
            "string"
          ]
        }
      },
      "type": [
        "null",
        "object"
      ]
    },
    "SyncToken": {
      "type": [
        "null",
        "string"
      ]
    },
    "BillableTime": {
      "type": [
        "null",
        "boolean"
      ]
    },
    "DisplayName": {
      "type": [
        "null",
        "string"
      ]
    },
    "GivenName": {
      "type": [
        "null",
        "string"
      ]
    },
    "FamilyName": {
      "type": [
        "null",
        "string"
      ]
    },
    "Id": {
      "type": [
        "null",
        "string"
      ]
    },
    "domain": {
      "type": [
        "null",
        "string"
      ]
    },
    "Active": {
      "type": [
        "null",
        "boolean"
      ]
    },
    "BirthDate": {
      "type": [
        "null",
        "date-time"
      ]
    },
    "PrintOnCheckName": {
      "type": [
        "null",
        "string"
      ]
    },
    "MetaData": {
      "properties": {
        "CreateTime": {
          "type": [
            "null",
            "date-time"
          ]
        },
        "LastUpdatedTime": {
          "type": [
            "null",
            "date-time"
          ]
        }
      },
      "type": [
        "null",
        "object"
      ]
    },
    "PrimaryAddr": {
      "properties": {
        "Lat": {
          "type": [
            "null",
            "string"
          ]
        },
        "Id": {
          "type": [
            "null",
            "string"
          ]
        },
        "CountrySubDivisionCode": {
          "type": [
            "null",
            "string"
          ]
        },
        "City": {
          "type": [
            "null",
            "string"
          ]
        },
        "Long": {
          "type": [
            "null",
            "string"
          ]
        },
        "PostalCode": {
          "type": [
            "null",
            "string"
          ]
        },
        "Line1": {
          "type": [
            "null",
            "string"
          ]
        },
        "Line2": {
          "type": [
            "null",
            "string"
          ]
        },
        "Line3": {
          "type": [
            "null",
            "string"
          ]
        },
        "Line4": {
          "type": [
            "null",
            "string"
          ]
        },
        "Line5": {
          "type": [
            "null",
            "string"
          ]
        },
        "Country": {
          "type": [
            "null",
            "string"
          ]
        }
      },
      "type": [
        "null",
        "object"
      ]
    },
    "PrimaryEmailAddr": {
      "type": [
        "null",
        "object"
      ],
      "properties": {
        "Address": {
          "type": [
            "null",
            "string"
          ]
        }
      }
    },
    "Title": {
      "type": [
        "null",
        "string"
      ]
    },
    "MiddleName": {
      "type": [
        "null",
        "string"
      ]
    },
    "ReleasedDate": {
      "type": [
        "null",
        "date-time"
      ]
    },
    "Mobile": {
      "type": [
        "null",
        "object"
      ],
      "properties": {
        "FreeFormNumber": {
          "type": [
            "null",
            "string"
          ]
        }
      }
    },
    "Gender": {
      "type": [
        "null",
        "string"
      ]
    },
    "BillRate": {
      "type": [
        "null",
        "number"
      ]
    },
    "Suffix": {
      "type": [
        "null",
        "string"
      ]
    },
    "EmployeeNumber": {
      "type": [
        "null",
        "string"
      ]
    },
    "Organization": {
      "type": [
        "null",
        "boolean"
      ]
    },
    "SSN": {
      "type": [
        "null",
        "string"
      ]
    },
    "V4IDPseudonym": {
      "type": [
        "null",
        "string"
      ]
    },
    "CostRate": {
      "type": [
        "null",
        "number"
      ]
    }
  },
  "type": [
    "null",
    "object"
  ]
}