{
  "properties": {
    "address": {
      "type": [
        "string"
      ]
    },
    "address_2": {
      "type": [
        "string"
      ]
    },
    "cc_emails": {
      "type": [
        "string"
      ]
    },
    "city": {
      "type": [
        "string"
      ]
    },
    "country": {
      "type": [
        "string"
      ]
    },
    "created_at": {
      "type": [
        "date-time"
      ]
    },
    "first_name": {
      "type": [
        "string"
      ]
    },
    "id": {
      "type": [
        "integer"
      ]
    },
    "last_name": {
      "type": [
        "string"
      ]
    },
    "organization": {
      "type": [
        "string"
      ]
    },
    "parent_id": {
      "type": [
        "integer"
      ]
    },
    "phone": {
      "type": [
        "string"
      ]
    },
    "portal_customer_created_at": {
      "type": [
        "date-time"
      ]
    },
    "portal_invite_last_accepted_at": {
      "type": [
        "date-time"
      ]
    },
    "portal_invite_last_sent_at": {
      "type": [
        "date-time"
      ]
    },
    "reference": {
      "type": [
        "integer"
      ]
    },
    "state": {
      "type": [
        "string"
      ]
    },
    "tax_exempt": {
      "type": [
        "boolean"
      ]
    },
    "updated_at": {
      "type": [
        "date-time"
      ]
    },
    "vat_number": {
      "type": [
        "string"
      ]
    },
    "verified": {
      "type": [
        "boolean"
      ]
    },
    "zip": {
      "type": [
        "string"
      ]
    }
  }
}