{
  "properties": {
    "Active": {
      "type": [
        "null",
        "boolean"
      ]
    },
    "Id": {
      "type": [
        "null",
        "string"
      ]
    },
    "MetaData": {
      "properties": {
        "CreateTime": {
          "type": [
            "null",
            "date-time"
          ]
        },
        "LastUpdatedTime": {
          "type": [
            "null",
            "date-time"
          ]
        }
      },
      "type": [
        "null",
        "object"
      ]
    },
    "Name": {
      "type": [
        "null",
        "string"
      ]
    },
    "SyncToken": {
      "type": [
        "null",
        "string"
      ]
    },
    "domain": {
      "type": [
        "null",
        "string"
      ]
    },
    "sparse": {
      "type": [
        "null",
        "string"
      ]
    }
  },
  "type": [
    "null",
    "object"
  ]
}