{
  "properties": {
    "amount_source": {
      "type": [
        "string"
      ]
    },
    "contra_account_id": {
      "type": [
        "integer"
      ]
    },
    "date_created": {
      "type": [
        "date-time"
      ]
    },
    "date_last_modified": {
      "type": [
        "date-time"
      ]
    },
    "end_date_change_impact": {
      "type": [
        "string"
      ]
    },
    "end_date_source": {
      "type": [
        "string"
      ]
    },
    "expense_rule_id": {
      "type": [
        "integer"
      ]
    },
    "initial_amount": {
      "type": [
        "string"
      ]
    },
    "name": {
      "type": [
        "string"
      ]
    },
    "period_offset": {
      "type": [
        "integer"
      ]
    },
    "recognition_period": {
      "type": [
        "integer"
      ]
    },
    "reforecast_method": {
      "type": [
        "string"
      ]
    },
    "residual": {
      "type": [
        "string"
      ]
    },
    "rule_method": {
      "type": [
        "string"
      ]
    },
    "start_date_source": {
      "type": [
        "string"
      ]
    },
    "start_offset": {
      "type": [
        "integer"
      ]
    },
    "term_in_days": {
      "type": [
        "integer"
      ]
    },
    "term_in_months": {
      "type": [
        "integer"
      ]
    },
    "{{ system-column.record-hash }}": {
      "type": [
        "string"
      ]
    }
  }
}