{
  "properties": {
    "effectiveDate": {
      "type": [
        "string"
      ]
    },
    "externalId": {
      "type": [
        "string"
      ]
    },
    "inactive": {
      "type": [
        "boolean",
        " string"
      ]
    },
    "internalId": {
      "type": [
        "string"
      ]
    },
    "item": {
      "type": [
        "varies"
      ]
    },
    "memo": {
      "type": [
        "string"
      ]
    },
    "name": {
      "type": [
        "string"
      ]
    },
    "nullFieldList": {
      "type": [
        "varies"
      ]
    },
    "obsoleteDate": {
      "type": [
        "string"
      ]
    }
  }
}